fmllpsm/__init__.py
fmllpsm/application/services.py
fmllpsm/domain/entities.py
fmllpsm/domain/interfaces.py
fmllpsm/infrastructure/extractors/dino.py
fmllpsm/infrastructure/metrics/learned.py
fmllpsm/interfaces/facade.py
fmllpsm/py.typed
fmllpsm-0.1.0.dist-info/WHEEL
fmllpsm-0.1.0.dist-info/METADATA
fmllpsm-0.1.0.dist-info/RECORD
