Metadata-Version: 2.4
Name: fmllpsm
Version: 0.1.0
Summary: A foundational model based for low-level representation similarity metrics
Keywords: IQA,LPIPS,DINO,Computer Vision,Perceptual Metric
Author: chogerlate
Author-email: chogerlate <siwaratlaopromger4444@gmail.com>
License-Expression: BSD-2-Clause
Classifier: Programming Language :: Python :: 3
Classifier: License :: OSI Approved :: BSD License
Classifier: Operating System :: OS Independent
Classifier: Topic :: Scientific/Engineering :: Artificial Intelligence
Requires-Dist: open-clip-torch>=3.2.0
Requires-Dist: torch>=2.0.0
Requires-Dist: torchvision>=0.15.0
Requires-Dist: transformers>=4.30.0
Requires-Dist: numpy>=1.24.0
Requires-Python: >=3.10
Project-URL: Homepage, https://github.com/chogerlate/fmllpsm
Project-URL: Bug Tracker, https://github.com/chogerlate/fmllpsm/issues
